mkmkv_smart/__init__.py
mkmkv_smart/audio_detector.py
mkmkv_smart/audio_editor.py
mkmkv_smart/cli.py
mkmkv_smart/config.py
mkmkv_smart/language_detector.py
mkmkv_smart/language_utils.py
mkmkv_smart/matcher.py
mkmkv_smart/merger.py
mkmkv_smart/normalizer.py
mkmkv_smart/security_utils.py
mkmkv_smart-1.1.1.dist-info/METADATA
mkmkv_smart-1.1.1.dist-info/WHEEL
mkmkv_smart-1.1.1.dist-info/entry_points.txt
mkmkv_smart-1.1.1.dist-info/top_level.txt
mkmkv_smart-1.1.1.dist-info/RECORD
