Metadata-Version: 2.4
Name: mkmkv-smart
Version: 1.1.1
Summary: 智能视频字幕合并工具
Author-email: Sunn Yao <sunyour@gmail.com>
License-Expression: MIT
Project-URL: Homepage, https://github.com/cnsunyour/mkmkv-smart
Project-URL: Repository, https://github.com/cnsunyour/mkmkv-smart
Project-URL: Issues, https://github.com/cnsunyour/mkmkv-smart/issues
Project-URL: Changelog, https://github.com/cnsunyour/mkmkv-smart/blob/main/CHANGELOG.md
Keywords: mkvmerge,subtitle,video,mkv,fuzzy-matching
Classifier: Development Status :: 5 - Production/Stable
Classifier: Intended Audience :: End Users/Desktop
Classifier: Programming Language :: Python :: 3
Classifier: Programming Language :: Python :: 3.8
Classifier: Programming Language :: Python :: 3.9
Classifier: Programming Language :: Python :: 3.10
Classifier: Programming Language :: Python :: 3.11
Classifier: Programming Language :: Python :: 3.12
Classifier: Programming Language :: Python :: 3.13
Classifier: Topic :: Multimedia :: Video
Classifier: Topic :: Utilities
Requires-Python: >=3.8
Requires-Dist: rapidfuzz>=3.0.0
Requires-Dist: pyyaml>=6.0
Requires-Dist: rich>=13.0.0
Requires-Dist: langdetect>=1.0.9
Requires-Dist: scipy>=1.9.0
Provides-Extra: dev
Requires-Dist: pytest>=7.0.0; extra == "dev"
Requires-Dist: pytest-cov>=4.0.0; extra == "dev"
Requires-Dist: black>=23.0.0; extra == "dev"
Requires-Dist: mypy>=1.0.0; extra == "dev"
Provides-Extra: audio
Requires-Dist: faster-whisper>=1.0.0; extra == "audio"
